minutedb/__init__.py
minutedb/minutedb.py
minutedb/utils.py
MinuteDB-0.0.3.dist-info/LICENSE
MinuteDB-0.0.3.dist-info/METADATA
MinuteDB-0.0.3.dist-info/WHEEL
MinuteDB-0.0.3.dist-info/top_level.txt
MinuteDB-0.0.3.dist-info/RECORD
