Metadata-Version: 2.1
Name: MinuteDB
Version: 0.0.3
Summary: MinuteDB is a simple local database written in Python that provides basic CRUD (Create, Read, Update, Delete) operations on a local file-based database.
Home-page: https://github.com/sandeepgit32/MinuteDB.git
Author: Sandip Karar
Author-email: sandeep7632@gmail.com
Classifier: Programming Language :: Python :: 3
Classifier: License :: OSI Approved :: MIT License
Classifier: Operating System :: OS Independent
Requires-Python: >=3.7
License-File: LICENSE
Requires-Dist: filelock
